setup.py
distributions/Binomialdistribution.py
distributions/Gaussiandistribution.py
distributions/Generaldistribution.py
distributions/__init__.py
distributions_tl1.egg-info/PKG-INFO
distributions_tl1.egg-info/SOURCES.txt
distributions_tl1.egg-info/dependency_links.txt
distributions_tl1.egg-info/not-zip-safe
distributions_tl1.egg-info/top_level.txt